MANIFEST.in
README.txt
setup.py
medialog/.DS_Store
medialog/__init__.py
medialog.dexterityview.egg-info/PKG-INFO
medialog.dexterityview.egg-info/SOURCES.txt
medialog.dexterityview.egg-info/dependency_links.txt
medialog.dexterityview.egg-info/entry_points.txt
medialog.dexterityview.egg-info/namespace_packages.txt
medialog.dexterityview.egg-info/not-zip-safe
medialog.dexterityview.egg-info/requires.txt
medialog.dexterityview.egg-info/top_level.txt
medialog/dexterityview/.DS_Store
medialog/dexterityview/__init__.py
medialog/dexterityview/configure.zcml
medialog/dexterityview/dexterity_image_display.pt
medialog/dexterityview/dexterity_view.pt
medialog/dexterityview/dexterity_view.py
medialog/dexterityview/dexterity_widget.pt
medialog/dexterityview/interfaces.py
medialog/dexterityview/vocabulary.py
medialog/dexterityview/profiles/.DS_Store
medialog/dexterityview/profiles/default/.DS_Store
medialog/dexterityview/profiles/default/browserlayer.xml
medialog/dexterityview/profiles/default/metadata.xml
medialog/dexterityview/profiles/default/registry.xml