Metadata-Version: 1.1
Name: medialog.dexterityview
Version: 0.1
Summary: A generic browser view for dexterity content
Home-page: http://github.com/espenmn/medialog.dexterityview
Author: Espen Moe-Nilssen
Author-email: espen@medialog.no
License: gpl
Keywords: dexterity view medialog plone
Platform: UNKNOWN
Classifier: Programming Language :: Python
